model_explorer_adapter/__init__.py
model_explorer_adapter/_pywrap_convert_wrapper.so
model_explorer_adapter-0.3.10.dist-info/METADATA
model_explorer_adapter-0.3.10.dist-info/WHEEL
model_explorer_adapter-0.3.10.dist-info/top_level.txt
model_explorer_adapter-0.3.10.dist-info/RECORD
